dropboxDiscord/__init__.py
dropboxDiscord-1.0.0.dist-info/METADATA
dropboxDiscord-1.0.0.dist-info/WHEEL
dropboxDiscord-1.0.0.dist-info/top_level.txt
dropboxDiscord-1.0.0.dist-info/RECORD
